ashpokealan10/__init__.py
ashpokealan10/alan.py
ashpokealan10/pokemon.csv
ashpokealan10/random_pokemon.py
ashpokealan10-1.0.1.dist-info/METADATA
ashpokealan10-1.0.1.dist-info/WHEEL
ashpokealan10-1.0.1.dist-info/top_level.txt
ashpokealan10-1.0.1.dist-info/RECORD
