Metadata-Version: 2.1
Name: ashpokealan10
Version: 1.0.1
Summary: Libreria para generar un pokemon aleatorio
Home-page: UNKNOWN
Author: alan27
Author-email: alanurielsanchezhernandez9@gmail.com
License: UNKNOWN
Platform: UNKNOWN
Requires-Dist: pandas
